.gitignore
README.rst
bootstrap.py
buildout.cfg
setup.py
collective/__init__.py
collective.js.nivoslider.egg-info/PKG-INFO
collective.js.nivoslider.egg-info/SOURCES.txt
collective.js.nivoslider.egg-info/dependency_links.txt
collective.js.nivoslider.egg-info/entry_points.txt
collective.js.nivoslider.egg-info/namespace_packages.txt
collective.js.nivoslider.egg-info/not-zip-safe
collective.js.nivoslider.egg-info/requires.txt
collective.js.nivoslider.egg-info/top_level.txt
collective/js/__init__.py
collective/js/nivoslider/README
collective/js/nivoslider/__init__.py
collective/js/nivoslider/configure.zcml
collective/js/nivoslider/demo.pt
collective/js/nivoslider/demo.zcml
collective/js/nivoslider/license.txt
collective/js/nivoslider/upgrades.py
collective/js/nivoslider/profiles/default/cssregistry.xml
collective/js/nivoslider/profiles/default/jsregistry.xml
collective/js/nivoslider/profiles/default/metadata.xml
collective/js/nivoslider/profiles/uninstall/jsregistry.xml
collective/js/nivoslider/resources/jquery.nivo.slider.js
collective/js/nivoslider/resources/jquery.nivo.slider.pack.js
collective/js/nivoslider/resources/license.txt
collective/js/nivoslider/resources/nivo-slider.css
collective/js/nivoslider/resources/demo/.DS_Store
collective/js/nivoslider/resources/demo/dev7logo.png
collective/js/nivoslider/resources/demo/nemo.jpg
collective/js/nivoslider/resources/demo/toystory.jpg
collective/js/nivoslider/resources/demo/up.jpg
collective/js/nivoslider/resources/demo/walle.jpg
collective/js/nivoslider/resources/themes/default/arrows.png
collective/js/nivoslider/resources/themes/default/bullets.png
collective/js/nivoslider/resources/themes/default/default.css
collective/js/nivoslider/resources/themes/default/loading.gif
collective/js/nivoslider/tests/__init__.py
collective/js/nivoslider/tests/base.py
collective/js/nivoslider/tests/test_setup.py
docs/HISTORY.txt