Metadata-Version: 1.0
Name: collective.js.nivoslider
Version: 3.0.1.1
Summary: JQuery Nivogallery plugin as browser resource
Home-page: http://github.com/espenmn/collective.js.nivoslider
Author: Espen Moe-Nillssen
Author-email: espen@medialog.no
License: GPL
Keywords: nivo gallery nivoslider slider plone plonetruegallery
Platform: UNKNOWN
Classifier: Programming Language :: Python
